launchpadcli/__init__.py
launchpadcli/auth.py
launchpadcli/cli.py
launchpadcli/ppa.py
launchpad_cli-0.1.7.dist-info/LICENSE
launchpad_cli-0.1.7.dist-info/METADATA
launchpad_cli-0.1.7.dist-info/WHEEL
launchpad_cli-0.1.7.dist-info/entry_points.txt
launchpad_cli-0.1.7.dist-info/top_level.txt
launchpad_cli-0.1.7.dist-info/RECORD
