Metadata-Version: 2.1
Name: launchpad-cli
Version: 0.1.7
Summary: CLI tools for Launchpad and PPA
Home-page: https://github.com/norioxkimura/launchpad-cli
Author: Norio Kimura
Author-email: kimura@monad.tv
License: MIT
Platform: UNKNOWN
Requires-Dist: six
Requires-Dist: launchpadlib
Requires-Dist: click
Provides-Extra: dev
Requires-Dist: pytest; extra == 'dev'
Requires-Dist: tox; extra == 'dev'
